sangmyung_univ_auth/__init__.py
sangmyung_univ_auth/auth.py
sangmyung_univ_auth/response.py
sangmyung_univ_auth/authenticator/__init__.py
sangmyung_univ_auth/authenticator/ecampus_session.py
sangmyung_univ_auth/authenticator/portal_ssotoken.py
tests/__init__.py
tests/test_auth.py
sangmyung_univ_auth-1.2.2.dist-info/LICENSE
sangmyung_univ_auth-1.2.2.dist-info/METADATA
sangmyung_univ_auth-1.2.2.dist-info/WHEEL
sangmyung_univ_auth-1.2.2.dist-info/top_level.txt
sangmyung_univ_auth-1.2.2.dist-info/RECORD
