Metadata-Version: 2.1
Name: sangmyung-univ-auth
Version: 1.2.2
Summary: Sangmyung University Students Account Authentication.
Home-page: https://github.com/hyunmin0317/sangmyung-univ-auth
Author: Choi Hyun Min
Author-email: choihm9903@naver.com
License: MIT
Keywords: sangmyung univ auth
Platform: any
Classifier: Programming Language :: Python :: 3
Classifier: License :: OSI Approved :: MIT License
Classifier: Operating System :: OS Independent
Requires-Python: >=3.6
License-File: LICENSE
